CHANGELOG.txt
LICENCE.txt
MANIFEST.in
README.md
setup.py
calculator/__init__.py
calculator.egg-info/PKG-INFO
calculator.egg-info/SOURCES.txt
calculator.egg-info/dependency_links.txt
calculator.egg-info/top_level.txt